indoxArcg/__init__.py
indoxArcg/indoxRag.py
indoxArcg/utils.py
indoxArcg/core/__init__.py
indoxArcg/core/base_llm.py
indoxArcg/core/document_object.py
indoxArcg/core/embeddings.py
indoxArcg/core/vectorstore.py
indoxArcg/data_connectors/__init__.py
indoxArcg/data_connectors/arxiv.py
indoxArcg/data_connectors/discord.py
indoxArcg/data_connectors/github.py
indoxArcg/data_connectors/guten.py
indoxArcg/data_connectors/twitter.py
indoxArcg/data_connectors/wikipedia.py
indoxArcg/data_connectors/youtube.py
indoxArcg/data_connectors/google/__init__.py
indoxArcg/data_connectors/google/googleChat.py
indoxArcg/data_connectors/google/googleDoc.py
indoxArcg/data_connectors/google/googleDrive.py
indoxArcg/data_connectors/google/goolgeSheet.py
indoxArcg/data_connectors/google/maps_search.py
indoxArcg/data_connectors/utils/__init__.py
indoxArcg/data_connectors/utils/document.py
indoxArcg/data_loader_splitter/__init__.py
indoxArcg/data_loader_splitter/ClusteredSplit/Clustering.py
indoxArcg/data_loader_splitter/ClusteredSplit/Embed.py
indoxArcg/data_loader_splitter/ClusteredSplit/EmbedClusterSummarize.py
indoxArcg/data_loader_splitter/ClusteredSplit/__init__.py
indoxArcg/data_loader_splitter/ClusteredSplit/cs_utils.py
indoxArcg/data_loader_splitter/ClusteredSplit/split.py
indoxArcg/data_loader_splitter/SimpleLoadAndSplit/__init__.py
indoxArcg/data_loader_splitter/SimpleLoadAndSplit/loader.py
indoxArcg/data_loader_splitter/SimpleLoadAndSplit/split.py
indoxArcg/data_loader_splitter/UnstructuredLoadAndSplit/__init__.py
indoxArcg/data_loader_splitter/UnstructuredLoadAndSplit/split.py
indoxArcg/data_loader_splitter/utils/__init__.py
indoxArcg/data_loader_splitter/utils/clean.py
indoxArcg/data_loader_splitter/utils/unstructured_utills.py
indoxArcg/data_loaders/__init__.py
indoxArcg/data_loaders/bs4.py
indoxArcg/data_loaders/csv.py
indoxArcg/data_loaders/docling.py
indoxArcg/data_loaders/docx.py
indoxArcg/data_loaders/excel.py
indoxArcg/data_loaders/html.py
indoxArcg/data_loaders/joblib.py
indoxarcg-0.0.14.dist-info/licenses/LICENSE
indoxarcg-0.0.14.dist-info/METADATA
indoxarcg-0.0.14.dist-info/WHEEL
indoxarcg-0.0.14.dist-info/top_level.txt
indoxarcg-0.0.14.dist-info/RECORD
