Metadata-Version: 2.4
Name: indoxArcg
Version: 0.0.14
Summary: Indox Retrieval Augmentation
Home-page: https://github.com/osllmai/inDox/libs/indoxArcg
Author: osllm.ai
Author-email: ashkan@nematifamilyfundation.onmicrosoft.com
License: AGPL-3.0
Keywords: RAG,CAG,LLM,retrieval-augmented generation,machine learning,natural language processing,NLP,AI,deep learning,language models
Classifier: Development Status :: 3 - Alpha
Classifier: Intended Audience :: Developers
Classifier: Topic :: Software Development :: Build Tools
Classifier: License :: OSI Approved :: GNU Affero General Public License v3 or later (AGPLv3+)
Classifier: Programming Language :: Python :: 3.9
Classifier: Programming Language :: Python :: 3.10
Classifier: Programming Language :: Python :: 3.11
Classifier: Programming Language :: Python :: 3.12
Requires-Python: >=3.9
License-File: LICENSE
Requires-Dist: dotenv
Requires-Dist: latex2markdown
Requires-Dist: loguru
Requires-Dist: nltk
Requires-Dist: numpy
Requires-Dist: openai
Requires-Dist: pandas
Requires-Dist: pillow_heif
Requires-Dist: protobuf
Requires-Dist: pydantic
Requires-Dist: PyPDF2
Requires-Dist: python-dotenv
Requires-Dist: rank_bm25
Requires-Dist: Requests
Requires-Dist: semantic-text-splitter
Requires-Dist: setuptools
Requires-Dist: tenacity
Requires-Dist: tiktoken
Requires-Dist: tokenizers
Requires-Dist: transformers
Requires-Dist: umap_learn
Requires-Dist: unstructured
Dynamic: author
Dynamic: author-email
Dynamic: classifier
Dynamic: description
Dynamic: description-content-type
Dynamic: home-page
Dynamic: keywords
Dynamic: license
Dynamic: license-file
Dynamic: requires-dist
Dynamic: requires-python
Dynamic: summary
